D_FLIP_FLOP/d_ff.v
module d_flipflop (
    input clk,
    input d,
    output reg q
);

always @(posedge clk) begin
    q <= d;
end

endmodule

D_FLIP_FLOP/tb_d_ff.v
`timescale 1ns/1ps

module tb_d_flipflop;

reg clk;
reg d;
wire q;

// Instantiate D Flip-Flop
d_flipflop uut (
    .clk(clk),
    .d(d),
    .q(q)
);

// Clock generation (10ns period)
always #5 clk = ~clk;

initial begin
    // GTKWave dump
    $dumpfile("d_flipflop.vcd");
    $dumpvars(0, tb_d_flipflop);

    // Initialize signals
    clk = 0;
    d = 0;

    // Display header
    $display("Time\tCLK\tD\tQ");
    $display("-------------------------");

    // Monitor changes
    $monitor("%0t\t%b\t%b\t%b", $time, clk, d, q);

    // Apply test vectors
    #7  d = 1;
    #10 d = 0;
    #10 d = 1;
    #10 d = 1;
    #10 d = 0;

    #10 $finish;
end

endmodule

D_FLIP_FLOP/d_flipflop.vcd
$date
	Fri Feb  6 18:01:23 2026
$end
$version
	Icarus Verilog
$end
$timescale
	1ps
$end
$scope module tb_d_flipflop $end
$var wire 1 ! q $end
$var reg 1 " clk $end
$var reg 1 # d $end
$scope module uut $end
$var wire 1 " clk $end
$var wire 1 # d $end
$var reg 1 ! q $end
$upscope $end
$upscope $end
$enddefinitions $end
$comment Show the parameter values. $end
$dumpall
$end
#0
$dumpvars
0#
0"
x!
$end
#5000
0!
1"
#7000
1#
#10000
0"
#15000
1!
1"
#17000
0#
#20000
0"
#25000
0!
1"
#27000
1#
#30000
0"
#35000
1!
1"
#40000
0"
#45000
1"
#47000
0#
#50000
0"
#55000
0!
1"
